<annotation>
	<folder>JPEGImages</folder>
	<filename>a273.jpg</filename>
	<path>E:\construction_datasets_2\JPEGImages\a273.jpg</path>
	<source>
		<database>Unknown</database>
	</source>
	<size>
		<width>500</width>
		<height>375</height>
		<depth>3</depth>
	</size>
	<segmented>0</segmented>
	<object>
		<name>sign</name>
		<pose>Unspecified</pose>
		<truncated>0</truncated>
		<difficult>0</difficult>
		<bndbox>
			<xmin>8</xmin>
			<ymin>106</ymin>
			<xmax>412</xmax>
			<ymax>321</ymax>
		</bndbox>
	</object>
</annotation>
