<annotation>
	<folder>photo</folder>
	<filename>cesun598.jpg</filename>
	<path>E:\make_dataset_yolo\photo\cesun598.jpg</path>
	<source>
		<database>Unknown</database>
	</source>
	<size>
		<width>600</width>
		<height>600</height>
		<depth>3</depth>
	</size>
	<segmented>0</segmented>
	<object>
		<name>sign</name>
		<pose>Unspecified</pose>
		<truncated>0</truncated>
		<difficult>0</difficult>
		<bndbox>
			<xmin>224</xmin>
			<ymin>301</ymin>
			<xmax>474</xmax>
			<ymax>378</ymax>
		</bndbox>
	</object>
</annotation>
