<annotation>
	<folder>JPEGImages</folder>
	<filename>D120.jpg</filename>
	<path>E:\construction_datasets_1\JPEGImages\D120.jpg</path>
	<source>
		<database>Unknown</database>
	</source>
	<size>
		<width>600</width>
		<height>469</height>
		<depth>3</depth>
	</size>
	<segmented>0</segmented>
	<object>
		<name>safetyhat</name>
		<pose>Unspecified</pose>
		<truncated>0</truncated>
		<difficult>0</difficult>
		<bndbox>
			<xmin>202</xmin>
			<ymin>126</ymin>
			<xmax>336</xmax>
			<ymax>345</ymax>
		</bndbox>
	</object>
</annotation>
