<annotation>
	<folder>JPEGImages</folder>
	<filename>D69.jpg</filename>
	<path>E:\construction_datasets_1\JPEGImages\D69.jpg</path>
	<source>
		<database>Unknown</database>
	</source>
	<size>
		<width>2000</width>
		<height>1500</height>
		<depth>3</depth>
	</size>
	<segmented>0</segmented>
	<object>
		<name>pedestrian</name>
		<pose>Unspecified</pose>
		<truncated>1</truncated>
		<difficult>0</difficult>
		<bndbox>
			<xmin>353</xmin>
			<ymin>1</ymin>
			<xmax>1107</xmax>
			<ymax>1300</ymax>
		</bndbox>
	</object>
</annotation>
