<annotation>
	<folder>JPEGImages</folder>
	<filename>DJI (444).jpg</filename>
	<path>D:\UAV\JPEGImages\DJI (444).jpg</path>
	<source>
		<database>Unknown</database>
	</source>
	<size>
		<width>1920</width>
		<height>1080</height>
		<depth>3</depth>
	</size>
	<segmented>0</segmented>
	<object>
		<name>safetyhat</name>
		<pose>Unspecified</pose>
		<truncated>0</truncated>
		<difficult>0</difficult>
		<bndbox>
			<xmin>438</xmin>
			<ymin>449</ymin>
			<xmax>514</xmax>
			<ymax>601</ymax>
		</bndbox>
	</object>
	<object>
		<name>safetyhat</name>
		<pose>Unspecified</pose>
		<truncated>0</truncated>
		<difficult>0</difficult>
		<bndbox>
			<xmin>288</xmin>
			<ymin>106</ymin>
			<xmax>392</xmax>
			<ymax>281</ymax>
		</bndbox>
	</object>
	<object>
		<name>pedestrian</name>
		<pose>Unspecified</pose>
		<truncated>0</truncated>
		<difficult>0</difficult>
		<bndbox>
			<xmin>479</xmin>
			<ymin>633</ymin>
			<xmax>611</xmax>
			<ymax>763</ymax>
		</bndbox>
	</object>
	<object>
		<name>safetyhat</name>
		<pose>Unspecified</pose>
		<truncated>0</truncated>
		<difficult>0</difficult>
		<bndbox>
			<xmin>920</xmin>
			<ymin>745</ymin>
			<xmax>1017</xmax>
			<ymax>899</ymax>
		</bndbox>
	</object>
	<object>
		<name>pedestrian</name>
		<pose>Unspecified</pose>
		<truncated>1</truncated>
		<difficult>0</difficult>
		<bndbox>
			<xmin>891</xmin>
			<ymin>957</ymin>
			<xmax>986</xmax>
			<ymax>1080</ymax>
		</bndbox>
	</object>
	<object>
		<name>safetyhat</name>
		<pose>Unspecified</pose>
		<truncated>0</truncated>
		<difficult>0</difficult>
		<bndbox>
			<xmin>1026</xmin>
			<ymin>849</ymin>
			<xmax>1107</xmax>
			<ymax>1014</ymax>
		</bndbox>
	</object>
	<object>
		<name>pedestrian</name>
		<pose>Unspecified</pose>
		<truncated>0</truncated>
		<difficult>0</difficult>
		<bndbox>
			<xmin>1038</xmin>
			<ymin>743</ymin>
			<xmax>1113</xmax>
			<ymax>878</ymax>
		</bndbox>
	</object>
	<object>
		<name>safetyhat</name>
		<pose>Unspecified</pose>
		<truncated>0</truncated>
		<difficult>0</difficult>
		<bndbox>
			<xmin>1219</xmin>
			<ymin>535</ymin>
			<xmax>1295</xmax>
			<ymax>707</ymax>
		</bndbox>
	</object>
	<object>
		<name>safetyhat</name>
		<pose>Unspecified</pose>
		<truncated>0</truncated>
		<difficult>0</difficult>
		<bndbox>
			<xmin>1454</xmin>
			<ymin>101</ymin>
			<xmax>1556</xmax>
			<ymax>201</ymax>
		</bndbox>
	</object>
	<object>
		<name>safetyhat</name>
		<pose>Unspecified</pose>
		<truncated>1</truncated>
		<difficult>0</difficult>
		<bndbox>
			<xmin>1298</xmin>
			<ymin>957</ymin>
			<xmax>1381</xmax>
			<ymax>1080</ymax>
		</bndbox>
	</object>
	<object>
		<name>pedestrian</name>
		<pose>Unspecified</pose>
		<truncated>0</truncated>
		<difficult>0</difficult>
		<bndbox>
			<xmin>1484</xmin>
			<ymin>659</ymin>
			<xmax>1569</xmax>
			<ymax>807</ymax>
		</bndbox>
	</object>
</annotation>
