<annotation>
	<folder>photo</folder>
	<filename>flip315.jpg</filename>
	<path>E:\make_dataset_yolo\photo\flip315.jpg</path>
	<source>
		<database>Unknown</database>
	</source>
	<size>
		<width>141</width>
		<height>180</height>
		<depth>3</depth>
	</size>
	<segmented>0</segmented>
	<object>
		<name>sign</name>
		<pose>Unspecified</pose>
		<truncated>1</truncated>
		<difficult>0</difficult>
		<bndbox>
			<xmin>1</xmin>
			<ymin>82</ymin>
			<xmax>91</xmax>
			<ymax>120</ymax>
		</bndbox>
	</object>
	<object>
		<name>sign</name>
		<pose>Unspecified</pose>
		<truncated>1</truncated>
		<difficult>0</difficult>
		<bndbox>
			<xmin>100</xmin>
			<ymin>80</ymin>
			<xmax>141</xmax>
			<ymax>119</ymax>
		</bndbox>
	</object>
	<object>
		<name>sign</name>
		<pose>Unspecified</pose>
		<truncated>1</truncated>
		<difficult>0</difficult>
		<bndbox>
			<xmin>1</xmin>
			<ymin>52</ymin>
			<xmax>84</xmax>
			<ymax>80</ymax>
		</bndbox>
	</object>
	<object>
		<name>sign</name>
		<pose>Unspecified</pose>
		<truncated>1</truncated>
		<difficult>0</difficult>
		<bndbox>
			<xmin>93</xmin>
			<ymin>56</ymin>
			<xmax>141</xmax>
			<ymax>80</ymax>
		</bndbox>
	</object>
	<object>
		<name>sign</name>
		<pose>Unspecified</pose>
		<truncated>0</truncated>
		<difficult>0</difficult>
		<bndbox>
			<xmin>83</xmin>
			<ymin>35</ymin>
			<xmax>140</xmax>
			<ymax>54</ymax>
		</bndbox>
	</object>
	<object>
		<name>sign</name>
		<pose>Unspecified</pose>
		<truncated>0</truncated>
		<difficult>0</difficult>
		<bndbox>
			<xmin>5</xmin>
			<ymin>34</ymin>
			<xmax>78</xmax>
			<ymax>53</ymax>
		</bndbox>
	</object>
	<object>
		<name>sign</name>
		<pose>Unspecified</pose>
		<truncated>0</truncated>
		<difficult>0</difficult>
		<bndbox>
			<xmin>15</xmin>
			<ymin>19</ymin>
			<xmax>72</xmax>
			<ymax>35</ymax>
		</bndbox>
	</object>
	<object>
		<name>sign</name>
		<pose>Unspecified</pose>
		<truncated>0</truncated>
		<difficult>0</difficult>
		<bndbox>
			<xmin>77</xmin>
			<ymin>22</ymin>
			<xmax>133</xmax>
			<ymax>37</ymax>
		</bndbox>
	</object>
	<object>
		<name>sign</name>
		<pose>Unspecified</pose>
		<truncated>0</truncated>
		<difficult>0</difficult>
		<bndbox>
			<xmin>21</xmin>
			<ymin>9</ymin>
			<xmax>70</xmax>
			<ymax>21</ymax>
		</bndbox>
	</object>
	<object>
		<name>sign</name>
		<pose>Unspecified</pose>
		<truncated>0</truncated>
		<difficult>0</difficult>
		<bndbox>
			<xmin>73</xmin>
			<ymin>10</ymin>
			<xmax>119</xmax>
			<ymax>22</ymax>
		</bndbox>
	</object>
</annotation>
