<annotation>
	<folder>JPEGImages</folder>
	<filename>t123.jpg</filename>
	<path>F:\construction_datasets\JPEGImages\t123.jpg</path>
	<source>
		<database>Unknown</database>
	</source>
	<size>
		<width>800</width>
		<height>533</height>
		<depth>3</depth>
	</size>
	<segmented>0</segmented>
	<object>
		<name>truck</name>
		<pose>Unspecified</pose>
		<truncated>0</truncated>
		<difficult>0</difficult>
		<bndbox>
			<xmin>33</xmin>
			<ymin>144</ymin>
			<xmax>768</xmax>
			<ymax>422</ymax>
		</bndbox>
	</object>
</annotation>
